guider/__init__.py
guider/__main__.py
guider/guider.py
guider/test.py
guider-3.9.8993.data/data/share/guider/guider.conf
guider-3.9.8993.data/data/share/man/man1/guider.1
guider-3.9.8993.data/scripts/guider
guider-3.9.8993.dist-info/LICENSE
guider-3.9.8993.dist-info/METADATA
guider-3.9.8993.dist-info/WHEEL
guider-3.9.8993.dist-info/top_level.txt
guider-3.9.8993.dist-info/RECORD
