Metadata-Version: 2.1
Name: guider
Version: 3.9.8993
Summary: Unified performance analyzer
Home-page: https://github.com/iipeace/guider
Author: Peace Lee
Author-email: iipeace5@gmail.com
License: GPL2
Download-URL: https://github.com/iipeace/guider/archive/master.zip
Keywords: guider,linux,analyzer,performance,profile,trace,kernel
Platform: UNKNOWN
Classifier: Environment :: Console
Classifier: Natural Language :: English
Classifier: Operating System :: Android
Classifier: Operating System :: MacOS
Classifier: Operating System :: Microsoft :: Windows
Classifier: Operating System :: POSIX :: Linux
Classifier: Programming Language :: Python
Classifier: Topic :: Software Development :: Debuggers
Classifier: Topic :: Software Development :: Embedded Systems
Classifier: Topic :: Software Development :: Testing
Classifier: Topic :: System :: Filesystems
Classifier: Topic :: System :: Monitoring
Classifier: Topic :: System :: Operating System Kernels :: Linux
Classifier: License :: OSI Approved :: GNU General Public License v2 (GPLv2)
License-File: LICENSE
Requires-Dist: psutil ; platform_system != "Linux"
